rabbit_tunnel/__init__.py
rabbit_tunnel/__main__.py
rabbit_tunnel/_version.py
rabbit_tunnel-0.5.dist-info/LICENSE
rabbit_tunnel-0.5.dist-info/METADATA
rabbit_tunnel-0.5.dist-info/WHEEL
rabbit_tunnel-0.5.dist-info/entry_points.txt
rabbit_tunnel-0.5.dist-info/top_level.txt
rabbit_tunnel-0.5.dist-info/RECORD
